datasette_yaml/__init__.py
datasette_yaml-0.1.1.dist-info/METADATA
datasette_yaml-0.1.1.dist-info/WHEEL
datasette_yaml-0.1.1.dist-info/entry_points.txt
datasette_yaml-0.1.1.dist-info/top_level.txt
datasette_yaml-0.1.1.dist-info/RECORD
