Metadata-Version: 2.1
Name: datasette-yaml
Version: 0.1.1
Summary: Export Datasette records as YAML
Home-page: https://github.com/simonw/datasette-yaml
Author: Simon Willison
License: Apache License, Version 2.0
Project-URL: Issues, https://github.com/simonw/datasette-yaml/issues
Project-URL: CI, https://github.com/simonw/datasette-yaml/actions
Project-URL: Changelog, https://github.com/simonw/datasette-yaml/releases
Platform: UNKNOWN
Requires-Dist: datasette
Provides-Extra: test
Requires-Dist: pytest ; extra == 'test'
Requires-Dist: pytest-asyncio ; extra == 'test'
Requires-Dist: httpx ; extra == 'test'
Requires-Dist: sqlite-utils ; extra == 'test'
